locust_influx_integration/__init__.py
locust_influxdb_integration-0.0.1.dist-info/LICENSE
locust_influxdb_integration-0.0.1.dist-info/METADATA
locust_influxdb_integration-0.0.1.dist-info/WHEEL
locust_influxdb_integration-0.0.1.dist-info/top_level.txt
locust_influxdb_integration-0.0.1.dist-info/RECORD
